LICENSE
README.md
xpath_helper/__init__.py
xpath_helper/filter.py
xpath_helper/xpath_helper.py
xpath_helper-0.1.3.dist-info/LICENSE
xpath_helper-0.1.3.dist-info/WHEEL
xpath_helper-0.1.3.dist-info/METADATA
xpath_helper-0.1.3.dist-info/RECORD
