Metadata-Version: 2.1
Name: xpath-helper
Version: 0.1.3
Summary: A simple and chainnable API to build complicated XPath queries without the hassle.
Home-page: https://github.com/jrebecchi/xpath-helper
License: MIT
Keywords: xpath,helper,selenium,test,selector,scraping
Author: Johann Rebecchi
Author-email: jrebecchi@protonmail.com
Requires-Python: >=3.5
Classifier: Intended Audience :: Developers
Classifier: Intended Audience :: Information Technology
Classifier: License :: OSI Approved :: MIT License
Classifier: Natural Language :: English
Classifier: Operating System :: OS Independent
Classifier: Programming Language :: Python :: 3
Classifier: Programming Language :: Python :: 3.10
Classifier: Programming Language :: Python :: 3.5
Classifier: Programming Language :: Python :: 3.6
Classifier: Programming Language :: Python :: 3.7
Classifier: Programming Language :: Python :: 3.8
Classifier: Programming Language :: Python :: 3.9
Classifier: Topic :: Software Development :: Code Generators
Classifier: Topic :: Software Development :: Libraries :: Python Modules
Classifier: Topic :: Software Development :: Quality Assurance
Classifier: Topic :: Text Processing :: Markup
Classifier: Topic :: Text Processing :: Markup :: HTML
Classifier: Topic :: Text Processing :: Markup :: XML
Classifier: Topic :: Utilities
Classifier: Typing :: Typed
Project-URL: Repository, https://github.com/jrebecchi/xpath-helper
